cryolock/__init__.py
cryolock/_counterfeit.py
cryolock/_locks.py
cryolock-1.2.0.dist-info/licenses/COPYING
cryolock-1.2.0.dist-info/licenses/COPYING.LESSER
cryolock-1.2.0.dist-info/WHEEL
cryolock-1.2.0.dist-info/METADATA
cryolock-1.2.0.dist-info/RECORD
