Metadata-Version: 2.4
Name: cryolock
Version: 1.2.0
Summary: Systemwide pseudo-atomic lock mechanism for Python
Author-email: "Armin \"Era\" Ramezani" <e@4d2.org>
Requires-Python: >=2.7
License-Expression: LGPL-3.0-or-later
Classifier: Topic :: Security
Classifier: Intended Audience :: Developers
Classifier: Programming Language :: Python :: 3
Classifier: Programming Language :: Python :: 2.7
Classifier: Development Status :: 5 - Production/Stable
License-File: COPYING
License-File: COPYING.LESSER
Project-URL: Homepage, https://codeberg.org/3ra/cryolock
